{
    "conceptType": "relations",
    "id": "2EAFB927-A364-461f-B380-A55137332BC4",
    "meta": {
        "acceptsEntityOperations": [
            "Create",
            "Update",
            "Delete"
        ],
        "container": {
            "id": "FBF3A236-9335-4f0d-A935-54F947EDD7CA",
            "title": "Військово-облікова спеціальність",
            "type": "Accordion"
        },
        "formField": {
            "type": "form"
        },
        "multiple": false,
        "sortOrder": 32
    },
    "name": "mas",
    "target": "MASItem",
    "title": "Військово-облікова спеціальність"
}
